lightly/__init__.py
lightly/core.py
lightly/active_learning/__init__.py
lightly/active_learning/config/__init__.py
lightly/active_learning/config/selection_config.py
lightly/api/__init__.py
lightly/api/_version_checking.py
lightly/api/api_workflow_artifacts.py
lightly/api/api_workflow_client.py
lightly/api/api_workflow_collaboration.py
lightly/api/api_workflow_compute_worker.py
lightly/api/api_workflow_datasets.py
lightly/api/api_workflow_datasource_listing.py
lightly/api/api_workflow_datasources.py
lightly/api/api_workflow_download_dataset.py
lightly/api/api_workflow_export.py
lightly/api/api_workflow_predictions.py
lightly/api/api_workflow_selection.py
lightly/api/api_workflow_tags.py
lightly/api/api_workflow_upload_embeddings.py
lightly/api/api_workflow_upload_metadata.py
lightly/api/bitmask.py
lightly/api/download.py
lightly/api/patch.py
lightly/api/retry_utils.py
lightly/api/serve.py
lightly/api/swagger_api_client.py
lightly/api/swagger_rest_client.py
lightly/api/utils.py
lightly/cli/__init__.py
lightly/cli/_cli_simclr.py
lightly/cli/_helpers.py
lightly/cli/crop_cli.py
lightly/cli/download_cli.py
lightly/cli/embed_cli.py
lightly/cli/lightly_cli.py
lightly/cli/serve_cli.py
lightly/cli/train_cli.py
lightly/cli/version_cli.py
lightly/cli/config/__init__.py
lightly/cli/config/config.yaml
lightly/cli/config/get_config.py
lightly/cli/config/lightly-serve.yaml
lightly/data/__init__.py
lightly/data/_helpers.py
lightly/data/_image.py
lightly/data/_image_loaders.py
lightly/data/_utils.py
lightly/data/_video.py
lightly/data/collate.py
lightly/data/dataset.py
lightly/data/lightly_subset.py
lightly/data/multi_view_collate.py
lightly/embedding/__init__.py
lightly/embedding/_base.py
lightly/embedding/callbacks.py
lightly/embedding/embedding.py
lightly/loss/__init__.py
lightly/loss/barlow_twins_loss.py
lightly/loss/dcl_loss.py
lightly/loss/detcon_loss.py
lightly/loss/dino_loss.py
lightly/loss/emp_ssl_loss.py
lightly/loss/hypersphere_loss.py
lightly/loss/ibot_loss.py
lightly-1.5.21.dist-info/licenses/LICENSE.txt
lightly-1.5.21.dist-info/METADATA
lightly-1.5.21.dist-info/WHEEL
lightly-1.5.21.dist-info/entry_points.txt
lightly-1.5.21.dist-info/top_level.txt
lightly-1.5.21.dist-info/RECORD
