Metadata-Version: 2.4
Name: lightly
Version: 1.5.21
Summary: A deep learning package for self-supervised learning
Author-email: Lightly Team <team@lightly.ai>
License: Copyright (c) 2018 The Python Packaging Authority
Project-URL: Homepage, https://www.lightly.ai
Project-URL: Web-App, https://app.lightly.ai
Project-URL: Documentation, https://docs.lightly.ai
Project-URL: Github, https://github.com/lightly-ai/lightly
Project-URL: Discord, https://discord.gg/xvNJW94
Classifier: Development Status :: 5 - Production/Stable
Classifier: Intended Audience :: Developers
Classifier: Intended Audience :: Education
Classifier: Intended Audience :: Science/Research
Classifier: Topic :: Scientific/Engineering
Classifier: Topic :: Scientific/Engineering :: Artificial Intelligence
Classifier: Topic :: Scientific/Engineering :: Image Processing
Classifier: Topic :: Scientific/Engineering :: Mathematics
Classifier: Topic :: Software Development
Classifier: Topic :: Software Development :: Libraries
Classifier: Topic :: Software Development :: Libraries :: Python Modules
Classifier: Programming Language :: Python :: 3
Classifier: Programming Language :: Python :: 3.6
Classifier: Programming Language :: Python :: 3.7
Classifier: Programming Language :: Python :: 3.8
Classifier: Programming Language :: Python :: 3.9
Classifier: Programming Language :: Python :: 3.10
Classifier: Programming Language :: Python :: 3.11
Classifier: Programming Language :: Python :: 3.12
Classifier: License :: OSI Approved :: MIT License
Requires-Python: >=3.6
License-File: LICENSE.txt
Requires-Dist: certifi>=14.05.14
Requires-Dist: hydra-core>=1.0.0
Requires-Dist: lightly_utils~=0.0.0
Requires-Dist: numpy>=1.18.1
Requires-Dist: python_dateutil>=2.5.3
Requires-Dist: requests>=2.27.0
Requires-Dist: six>=1.10
Requires-Dist: tqdm>=4.44
Requires-Dist: torch
Requires-Dist: torchvision
Requires-Dist: pydantic>=1.10.5
Requires-Dist: pytorch_lightning>=1.0.4
Requires-Dist: urllib3>=1.25.3
Requires-Dist: aenum>=3.1.11
Provides-Extra: all
Requires-Dist: lightly[dev,matplotlib,minimal,timm,video]; extra == "all"
Provides-Extra: dev
Requires-Dist: sphinx; extra == "dev"
Requires-Dist: pylint; extra == "dev"
Requires-Dist: pytest; extra == "dev"
Requires-Dist: pytest-forked; extra == "dev"
Requires-Dist: pytest-xdist; extra == "dev"
Requires-Dist: pytest-mock; extra == "dev"
Requires-Dist: responses; extra == "dev"
Requires-Dist: docutils<=0.16; extra == "dev"
Requires-Dist: sphinx-copybutton; extra == "dev"
Requires-Dist: sphinx-design; extra == "dev"
Requires-Dist: sphinx-gallery; extra == "dev"
Requires-Dist: sphinx-tabs; extra == "dev"
Requires-Dist: sphinx-reredirects; extra == "dev"
Requires-Dist: sphinx_rtd_theme; extra == "dev"
Requires-Dist: matplotlib; extra == "dev"
Requires-Dist: pre-commit; extra == "dev"
Requires-Dist: opencv-python; extra == "dev"
Requires-Dist: scikit-learn; extra == "dev"
Requires-Dist: pandas; extra == "dev"
Requires-Dist: toml; extra == "dev"
Requires-Dist: torchmetrics; extra == "dev"
Requires-Dist: black==23.1.0; extra == "dev"
Requires-Dist: isort==5.11.5; extra == "dev"
Requires-Dist: mypy==1.4.1; extra == "dev"
Requires-Dist: types-python-dateutil; extra == "dev"
Requires-Dist: types-toml; extra == "dev"
Requires-Dist: types-requests; extra == "dev"
Requires-Dist: nbformat; extra == "dev"
Requires-Dist: jupytext; extra == "dev"
Provides-Extra: minimal
Requires-Dist: torch>=1.10.0; extra == "minimal"
Requires-Dist: torchvision>=0.11.0; extra == "minimal"
Requires-Dist: pytorch_lightning>=1.6; extra == "minimal"
Provides-Extra: openapi
Requires-Dist: python_dateutil>=2.5.3; extra == "openapi"
Requires-Dist: setuptools>=21.0.0; extra == "openapi"
Requires-Dist: urllib3>=1.25.3; extra == "openapi"
Requires-Dist: pydantic>=1.10.5; extra == "openapi"
Requires-Dist: aenum>=3.1.11; extra == "openapi"
Provides-Extra: timm
Requires-Dist: timm>=0.9.9; extra == "timm"
Provides-Extra: video
Requires-Dist: av>=8.0.3; extra == "video"
Provides-Extra: matplotlib
Requires-Dist: matplotlib>=3; extra == "matplotlib"
Dynamic: license-file
